renderctl/__init__.py
renderctl/main.py
renderctl/yamlrender.py
renderctl-1.0.2.dist-info/LICENSE
renderctl-1.0.2.dist-info/METADATA
renderctl-1.0.2.dist-info/WHEEL
renderctl-1.0.2.dist-info/entry_points.txt
renderctl-1.0.2.dist-info/top_level.txt
renderctl-1.0.2.dist-info/RECORD
