Metadata-Version: 2.1
Name: renderctl
Version: 1.0.2
Summary: RENDER CTL Tool
Home-page: https://github.com/penny1027/renderctl.git
Author: Penny
Author-email: 1058449090@qq.com
Maintainer: Penny
Maintainer-email: 1058449090@qq.com
License: MIT
Platform: any
